scikit_ika-0.0.6.dist-info/top_level.txt
scikit_ika-0.0.6.dist-info/RECORD
scikit_ika-0.0.6.dist-info/METADATA
scikit_ika-0.0.6.dist-info/LICENSE
scikit_ika-0.0.6.dist-info/WHEEL
skika/__init__.py
skika/ensemble.cpython-39-x86_64-linux-gnu.so
skika/hyper_parameter_tuning/__init__.py
skika/hyper_parameter_tuning/trees_arf/meta_feature_generator.py
skika/hyper_parameter_tuning/trees_arf/evaluate_prequential_and_adapt.py
skika/hyper_parameter_tuning/trees_arf/build_pareto_knowledge_trees.py
skika/hyper_parameter_tuning/trees_arf/__init__.py
skika/hyper_parameter_tuning/drift_detectors/build_pareto_knowledge_drifts.py
skika/hyper_parameter_tuning/drift_detectors/evaluate_drift_detection_knowledge.py
skika/hyper_parameter_tuning/drift_detectors/AutoDDM.py
skika/hyper_parameter_tuning/drift_detectors/evaluate_drift_detection_experiment.py
skika/hyper_parameter_tuning/drift_detectors/__init__.py
skika/data/wind_sim_generator.py
skika/data/hyper_plane_generator_redund.py
skika/data/stream_generator_redundancy_drift.py
skika/data/bernoulli_stream.py
skika/data/stream_generator.py
skika/data/reccurring_concept_stream.py
skika/data/random_rbf_generator_redund.py
skika/data/generate_dataset.py
skika/data/__init__.py
