Metadata-Version: 2.1
Name: scikit-ika
Version: 0.0.6
Summary: real-time lifelong machine learning
Home-page: https://github.com/scikit-ika/scikit-ika
Author: Team scikit-ika
Author-email: 
License: UNKNOWN
Platform: UNKNOWN
Classifier: Programming Language :: Python :: 3
Classifier: License :: OSI Approved :: BSD License
Classifier: Operating System :: OS Independent
Requires-Python: >=3.6
